{"nodes": [{"id": "home_ertval_code_zone_modules_filler_e2e_run_audit_suite_sh", "label": "run_audit_suite.sh", "file_type": "code", "source_file": "e2e/run_audit_suite.sh", "source_location": "L1", "metadata": {"language": "bash", "kind": "file"}}, {"id": "home_ertval_code_zone_modules_filler_e2e_run_audit_suite_sh__entry", "label": "run_audit_suite.sh script", "file_type": "code", "source_file": "e2e/run_audit_suite.sh", "source_location": "L1", "metadata": {"language": "bash", "kind": "bash_entrypoint"}}, {"id": "e2e_run_audit_suite_green", "label": "green()", "file_type": "code", "source_file": "e2e/run_audit_suite.sh", "source_location": "L11", "metadata": {"language": "bash", "kind": "bash_function"}}, {"id": "e2e_run_audit_suite_red", "label": "red()", "file_type": "code", "source_file": "e2e/run_audit_suite.sh", "source_location": "L12", "metadata": {"language": "bash", "kind": "bash_function"}}, {"id": "e2e_run_audit_suite_info", "label": "info()", "file_type": "code", "source_file": "e2e/run_audit_suite.sh", "source_location": "L13", "metadata": {"language": "bash", "kind": "bash_function"}}, {"id": "e2e_run_audit_suite_run_game", "label": "run_game()", "file_type": "code", "source_file": "e2e/run_audit_suite.sh", "source_location": "L32", "metadata": {"language": "bash", "kind": "bash_function"}}, {"id": "e2e_run_audit_suite_check_winrate", "label": "check_winrate()", "file_type": "code", "source_file": "e2e/run_audit_suite.sh", "source_location": "L55", "metadata": {"language": "bash", "kind": "bash_function"}}], "edges": [{"source": "home_ertval_code_zone_modules_filler_e2e_run_audit_suite_sh", "target": "home_ertval_code_zone_modules_filler_e2e_run_audit_suite_sh__entry", "relation": "contains", "confidence": "EXTRACTED", "source_file": "e2e/run_audit_suite.sh", "source_location": "L1", "weight": 1.0}, {"source": "home_ertval_code_zone_modules_filler_e2e_run_audit_suite_sh", "target": "e2e_run_audit_suite_green", "relation": "defines", "confidence": "EXTRACTED", "source_file": "e2e/run_audit_suite.sh", "source_location": "L11", "weight": 1.0}, {"source": "home_ertval_code_zone_modules_filler_e2e_run_audit_suite_sh", "target": "e2e_run_audit_suite_red", "relation": "defines", "confidence": "EXTRACTED", "source_file": "e2e/run_audit_suite.sh", "source_location": "L12", "weight": 1.0}, {"source": "home_ertval_code_zone_modules_filler_e2e_run_audit_suite_sh", "target": "e2e_run_audit_suite_info", "relation": "defines", "confidence": "EXTRACTED", "source_file": "e2e/run_audit_suite.sh", "source_location": "L13", "weight": 1.0}, {"source": "home_ertval_code_zone_modules_filler_e2e_run_audit_suite_sh", "target": "e2e_run_audit_suite_run_game", "relation": "defines", "confidence": "EXTRACTED", "source_file": "e2e/run_audit_suite.sh", "source_location": "L32", "weight": 1.0}, {"source": "home_ertval_code_zone_modules_filler_e2e_run_audit_suite_sh", "target": "e2e_run_audit_suite_check_winrate", "relation": "defines", "confidence": "EXTRACTED", "source_file": "e2e/run_audit_suite.sh", "source_location": "L55", "weight": 1.0}, {"source": "home_ertval_code_zone_modules_filler_e2e_run_audit_suite_sh__entry", "target": "e2e_run_audit_suite_info", "relation": "calls", "confidence": "EXTRACTED", "source_file": "e2e/run_audit_suite.sh", "source_location": "L18", "weight": 1.0, "context": "call"}, {"source": "home_ertval_code_zone_modules_filler_e2e_run_audit_suite_sh__entry", "target": "e2e_run_audit_suite_green", "relation": "calls", "confidence": "EXTRACTED", "source_file": "e2e/run_audit_suite.sh", "source_location": "L22", "weight": 1.0, "context": "call"}, {"source": "home_ertval_code_zone_modules_filler_e2e_run_audit_suite_sh__entry", "target": "e2e_run_audit_suite_red", "relation": "calls", "confidence": "EXTRACTED", "source_file": "e2e/run_audit_suite.sh", "source_location": "L24", "weight": 1.0, "context": "call"}, {"source": "home_ertval_code_zone_modules_filler_e2e_run_audit_suite_sh__entry", "target": "e2e_run_audit_suite_check_winrate", "relation": "calls", "confidence": "EXTRACTED", "source_file": "e2e/run_audit_suite.sh", "source_location": "L89", "weight": 1.0, "context": "call"}, {"source": "e2e_run_audit_suite_check_winrate", "target": "e2e_run_audit_suite_info", "relation": "calls", "confidence": "EXTRACTED", "source_file": "e2e/run_audit_suite.sh", "source_location": "L62", "weight": 1.0, "context": "call"}, {"source": "e2e_run_audit_suite_check_winrate", "target": "e2e_run_audit_suite_green", "relation": "calls", "confidence": "EXTRACTED", "source_file": "e2e/run_audit_suite.sh", "source_location": "L83", "weight": 1.0, "context": "call"}, {"source": "e2e_run_audit_suite_check_winrate", "target": "e2e_run_audit_suite_red", "relation": "calls", "confidence": "EXTRACTED", "source_file": "e2e/run_audit_suite.sh", "source_location": "L85", "weight": 1.0, "context": "call"}]}